sathi_lang/__init__.py
sathi_lang/__main__.py
sathi_lang-1.2.1.dist-info/licenses/LICENSE
sathi_lang-1.2.1.dist-info/METADATA
sathi_lang-1.2.1.dist-info/WHEEL
sathi_lang-1.2.1.dist-info/top_level.txt
sathi_lang-1.2.1.dist-info/RECORD
