Metadata-Version: 2.4
Name: sathi-lang
Version: 1.2.1
Summary: Sathi Language — a Nepali-inspired programming language blending creativity, culture, and code.
Home-page: https://github.com/nirajang20/Sathi-Language
Author: Nirajan Ghimire
Author-email: Nirajan Ghimire <nirajanghimire20@gmail.com>
License: MIT
Project-URL: Homepage, https://www.nirajang.com.np/sathi
Project-URL: Repository, https://github.com/nirajang20/Sathi-Language
Project-URL: Documentation, https://www.nirajang.com.np/sathi/docs
Classifier: Programming Language :: Python :: 3
Classifier: License :: OSI Approved :: MIT License
Classifier: Operating System :: OS Independent
Requires-Python: >=3.8
License-File: LICENSE
Dynamic: license-file
